src/__init__.py
src/__main__.py
src/koi/ast_printer.py
src/koi/class_type.py
src/koi/environment.py
src/koi/expr.py
src/koi/function_type.py
src/koi/interpreter.py
src/koi/koi.py
src/koi/koi_callable.py
src/koi/koi_class.py
src/koi/koi_function.py
src/koi/koi_instance.py
src/koi/koi_return_exception.py
src/koi/koi_runtime_error.py
src/koi/parser.py
src/koi/resolver.py
src/koi/scanner.py
src/koi/stmt.py
src/koi/token_type.py
src/koi/tokens.py
src/koi/types.py
src/koi/std/__init__.py
src/koi/std/clock.py
src/koi/std/fileio.py
src/koi/std/input.py
src/koi/std/numerable.py
src/koi/std/print.py
src/koi/std/strings.py
Koi_Language-2.0.0.dist-info/LICENSE
Koi_Language-2.0.0.dist-info/METADATA
Koi_Language-2.0.0.dist-info/WHEEL
Koi_Language-2.0.0.dist-info/entry_points.txt
Koi_Language-2.0.0.dist-info/top_level.txt
Koi_Language-2.0.0.dist-info/RECORD
